callisto/__init__.py
callisto/command.py
callisto/download.py
callisto/notification.py
callisto/pandas_statistics.py
callisto/stats_utils.py
callisto/var_utils.py
callisto/version.py
callisto_python-0.0.8.dist-info/LICENSE
callisto_python-0.0.8.dist-info/METADATA
callisto_python-0.0.8.dist-info/WHEEL
callisto_python-0.0.8.dist-info/top_level.txt
callisto_python-0.0.8.dist-info/RECORD
