Metadata-Version: 2.1
Name: callisto-python
Version: 0.0.8
Summary: Callisto python package
Home-page: https://app.callistoapp.com
Author: Oak City Labs
Author-email: team@oakcity.io
License: UNKNOWN
Platform: UNKNOWN
Classifier: Programming Language :: Python :: 3
Classifier: License :: OSI Approved :: MIT License
Classifier: Operating System :: OS Independent
Requires-Python: >=3
Requires-Dist: requests (<3,>=2.28.1)
Requires-Dist: tqdm (<5,>=4.64.0)
Provides-Extra: pandas
Requires-Dist: pandas (<3,>=1.0.0) ; extra == 'pandas'
